midea_lan/__init__.py
midea_lan/cli.py
midea_lan/cloud.py
midea_lan/const.py
midea_lan/crc8.py
midea_lan/device.py
midea_lan/discover.py
midea_lan/exceptions.py
midea_lan/message.py
midea_lan/packet_builder.py
midea_lan/py.typed
midea_lan/security.py
midea_lan/version.py
midea_lan/devices/__init__.py
midea_lan/devices/a1/__init__.py
midea_lan/devices/a1/message.py
midea_lan/devices/ac/__init__.py
midea_lan/devices/ac/message.py
midea_lan/devices/b0/__init__.py
midea_lan/devices/b0/message.py
midea_lan/devices/b1/__init__.py
midea_lan/devices/b1/message.py
midea_lan/devices/b3/__init__.py
midea_lan/devices/b3/message.py
midea_lan/devices/b4/__init__.py
midea_lan/devices/b4/message.py
midea_lan/devices/b6/__init__.py
midea_lan/devices/b6/message.py
midea_lan/devices/b8/__init__.py
midea_lan/devices/b8/const.py
midea_lan/devices/b8/message.py
midea_lan/devices/bf/__init__.py
midea_lan/devices/bf/message.py
midea_lan/devices/c2/__init__.py
midea_lan/devices/c2/message.py
midea_lan/devices/c3/__init__.py
midea_lan/devices/c3/const.py
midea_lan/devices/c3/message.py
midea_lan/devices/ca/__init__.py
midea_lan/devices/ca/message.py
midea_lan/devices/cc/__init__.py
midea_lan/devices/cc/message.py
midea_lan/devices/cd/__init__.py
midea_lan/devices/cd/message.py
midea_lan/devices/ce/__init__.py
midea_lan/devices/ce/message.py
midea_lan/devices/cf/__init__.py
midea_lan/devices/cf/message.py
midea_lan/devices/da/__init__.py
midea_lan/devices/da/message.py
midea_lan/devices/db/__init__.py
midea_lan/devices/db/message.py
midea_lan/devices/dc/__init__.py
midea_lan/devices/dc/message.py
midea_lan/devices/e1/__init__.py
midea_lan/devices/e1/message.py
midea_lan/devices/e2/__init__.py
midea_lan/devices/e2/message.py
midea_lan/devices/e3/__init__.py
midea_lan/devices/e3/message.py
midea_lan/devices/e6/__init__.py
midea_lan/devices/e6/message.py
midea_lan/devices/e8/__init__.py
midea_lan/devices/e8/message.py
midea_lan/devices/ea/__init__.py
midea_lan/devices/ea/message.py
midea_lan-0.1.0.dist-info/LICENSE
midea_lan-0.1.0.dist-info/METADATA
midea_lan-0.1.0.dist-info/WHEEL
midea_lan-0.1.0.dist-info/entry_points.txt
midea_lan-0.1.0.dist-info/top_level.txt
midea_lan-0.1.0.dist-info/RECORD
