Metadata-Version: 2.1
Name: midea-lan
Version: 0.1.0
Summary: Control your Midea M-Smart appliances via local area network
Home-page: https://github.com/midea-lan/midea-lan
Author: wuwentao, rokam, chemelli74, Necroneco
Author-email: wuwentao2000@126.com, lucas@mindello.com.br
License: MIT
Classifier: Programming Language :: Python :: 3
Classifier: License :: OSI Approved :: MIT License
Classifier: Operating System :: OS Independent
Requires-Python: >=3.11
License-File: LICENSE
Requires-Dist: aiofiles
Requires-Dist: aiohttp
Requires-Dist: colorlog
Requires-Dist: commonregex
Requires-Dist: defusedxml
Requires-Dist: deprecated
Requires-Dist: ifaddr
Requires-Dist: pycryptodome
Requires-Dist: platformdirs
